{"cameraMode":{"drawMode":0,"name":"Shaded","section":"Shading Mode"},"sceneLighting":true,"audioPlay":false,"sceneViewState":{"m_AlwaysRefresh":false,"showFog":true,"showSkybox":true,"showFlares":true,"showImageEffects":true,"showParticleSystems":true,"showVisualEffectGraphs":true,"m_FxEnabled":true},"in2DMode":false,"pivot":{"x":-9.040839195251465,"y":-3.711907148361206,"z":15.785797119140625},"rotation":{"x":-0.260797917842865,"y":-0.12784212827682496,"z":0.03593989089131355,"w":-0.9562264084815979},"size":7.399919033050537,"orthographic":false}